Metadata-Version: 1.0
Name: py-VOD
Version: 0.4.0
Summary: video on demand
Home-page: https://github.com/OpenJarbas/pyvod/
Author: jarbasAI
Author-email: jarbasai@mailfence.com
License: Apache
Platform: UNKNOWN
